odoo8_addon_pricelist_per_product-8.0.1.0.0.99.dev11-py2.7-nspkg.pth
odoo8_addon_pricelist_per_product-8.0.1.0.0.99.dev11.dist-info/DESCRIPTION.rst
odoo8_addon_pricelist_per_product-8.0.1.0.0.99.dev11.dist-info/METADATA
odoo8_addon_pricelist_per_product-8.0.1.0.0.99.dev11.dist-info/RECORD
odoo8_addon_pricelist_per_product-8.0.1.0.0.99.dev11.dist-info/WHEEL
odoo8_addon_pricelist_per_product-8.0.1.0.0.99.dev11.dist-info/metadata.json
odoo8_addon_pricelist_per_product-8.0.1.0.0.99.dev11.dist-info/namespace_packages.txt
odoo8_addon_pricelist_per_product-8.0.1.0.0.99.dev11.dist-info/top_level.txt
odoo_addons/pricelist_per_product/README.rst
odoo_addons/pricelist_per_product/__init__.py
odoo_addons/pricelist_per_product/__openerp__.py
odoo_addons/pricelist_per_product/install_view.xml
odoo_addons/pricelist_per_product/pricelist.py
odoo_addons/pricelist_per_product/pricelist_view.xml
odoo_addons/pricelist_per_product/product.py
odoo_addons/pricelist_per_product/product_view.xml
odoo_addons/pricelist_per_product/data/pricelist.xml
odoo_addons/pricelist_per_product/demo/product.pricelist.item.csv
odoo_addons/pricelist_per_product/i18n/ca.po
odoo_addons/pricelist_per_product/i18n/de.po
odoo_addons/pricelist_per_product/i18n/es.po
odoo_addons/pricelist_per_product/i18n/fr.po
odoo_addons/pricelist_per_product/i18n/it.po
odoo_addons/pricelist_per_product/i18n/pricelist_per_product.pot
odoo_addons/pricelist_per_product/i18n/sl.po
odoo_addons/pricelist_per_product/static/description/akretion.png
odoo_addons/pricelist_per_product/static/description/icon.png
odoo_addons/pricelist_per_product/static/description/index.html
odoo_addons/pricelist_per_product/static/description/mass.png
odoo_addons/pricelist_per_product/static/description/pricelist.png
odoo_addons/pricelist_per_product/static/description/product.png
odoo_addons/pricelist_per_product/tests/__init__.py
odoo_addons/pricelist_per_product/tests/test_create.py
